johnsnowlabs/__init__.py
johnsnowlabs/auto_nlp.py
johnsnowlabs/cli.py
johnsnowlabs/cli_v2.py
johnsnowlabs/finance.py
johnsnowlabs/legal.py
johnsnowlabs/medical.py
johnsnowlabs/nlp.py
johnsnowlabs/ocr.py
johnsnowlabs/settings.py
johnsnowlabs/viz.py
johnsnowlabs/abstract_base/__init__.py
johnsnowlabs/abstract_base/base_enum.py
johnsnowlabs/abstract_base/lib_resolver.py
johnsnowlabs/abstract_base/pydantic_model.py
johnsnowlabs/abstract_base/software_product.py
johnsnowlabs/auto_install/__init__.py
johnsnowlabs/auto_install/install_software.py
johnsnowlabs/auto_install/jsl_home.py
johnsnowlabs/auto_install/offline_install.py
johnsnowlabs/auto_install/softwares.py
johnsnowlabs/auto_install/databricks/__init__.py
johnsnowlabs/auto_install/databricks/databricks_utils.py
johnsnowlabs/auto_install/databricks/dbfs.py
johnsnowlabs/auto_install/emr/__init__.py
johnsnowlabs/auto_install/lib_resolvers/__init__.py
johnsnowlabs/auto_install/lib_resolvers/hc_installer.py
johnsnowlabs/auto_install/lib_resolvers/nlp_installer.py
johnsnowlabs/auto_install/lib_resolvers/ocr_installer.py
johnsnowlabs/cli_utils/__init__.py
johnsnowlabs/cli_utils/cli_flows.py
johnsnowlabs/py_models/__init__.py
johnsnowlabs/py_models/install_info.py
johnsnowlabs/py_models/jsl_secrets.py
johnsnowlabs/py_models/lib_version.py
johnsnowlabs/py_models/license_info.py
johnsnowlabs/py_models/primitive.py
johnsnowlabs/py_models/url_dependency.py
johnsnowlabs/utils/__init__.py
johnsnowlabs/utils/enums.py
johnsnowlabs/utils/env_utils.py
johnsnowlabs/utils/json_utils.py
johnsnowlabs/utils/my_jsl_api.py
johnsnowlabs/utils/pip_utils.py
johnsnowlabs/utils/sparksession_utils.py
johnsnowlabs/utils/venv_utils.py
johnsnowlabs/utils/health_checks/__init__.py
johnsnowlabs/utils/health_checks/hc.py
johnsnowlabs/utils/health_checks/nlp.py
johnsnowlabs/utils/health_checks/ocr.py
jsl_tmp1-4.0.47.dist-info/METADATA
jsl_tmp1-4.0.47.dist-info/WHEEL
jsl_tmp1-4.0.47.dist-info/top_level.txt
jsl_tmp1-4.0.47.dist-info/RECORD
