Metadata-Version: 2.1
Name: jsl-tmp1
Version: 4.0.47
Summary: TODO
Home-page: https://nlu.johnsnowlabs.com
Author: John Snow Labs
Author-email: christian@johnsnowlabs.com
License: UNKNOWN
Keywords: NLP spark development NLU
Platform: UNKNOWN
Classifier: Development Status :: 5 - Production/Stable
Classifier: Intended Audience :: Developers
Classifier: Topic :: Software Development :: Build Tools
Classifier: License :: OSI Approved :: Apache Software License
Classifier: Programming Language :: Python :: 2
Classifier: Programming Language :: Python :: 2.7
Classifier: Programming Language :: Python :: 3
Classifier: Programming Language :: Python :: 3.4
Classifier: Programming Language :: Python :: 3.5
Classifier: Programming Language :: Python :: 3.6
Requires-Dist: pyspark (==3.1.2)
Requires-Dist: spark-nlp (==4.1.0)
Requires-Dist: nlu (==4.0.1rc3)
Requires-Dist: spark-nlp-display
Requires-Dist: numpy
Requires-Dist: dataclasses
Requires-Dist: requests
Requires-Dist: databricks-api
Requires-Dist: pydantic
